wordsum/__init__.py
wordsum/_file_types/__init__.py
wordsum/_file_types/jupyter.py
wordsum/_file_types/markdown.py
wordsum/_io/__init__.py
wordsum/_io/read_files.py
wordsum/_util/__init__.py
wordsum/_util/file_locate.py
wordsum/setup.py
wordsum/word_sum.py
wordsum-0.1.3.dist-info/WHEEL
wordsum-0.1.3.dist-info/METADATA
wordsum-0.1.3.dist-info/RECORD
